digiformatter/__init__.py
digiformatter/formatter.py
digiformatter/logger.py
digiformatter/styles.py
tests/__init__.py
tests/test_digiformathandler.py
digiformatter-0.5.7.2.dist-info/METADATA
digiformatter-0.5.7.2.dist-info/WHEEL
digiformatter-0.5.7.2.dist-info/top_level.txt
digiformatter-0.5.7.2.dist-info/RECORD
