Metadata-Version: 2.1
Name: digiformatter
Version: 0.5.7.2
Summary: Make your terminals look spicy.
Home-page: https://github.com/DigiDuncan/DigiFormatter
Author: DigiDuncan
Author-email: digiduncan@gmail.com
License: UNKNOWN
Platform: UNKNOWN
Requires-Python: >=3
